[
    {
        "calling": "u138v000",
        "callee": "u138",
        "init_time": "2016-06-09 14:40:59",
        "answered": false,
        "duration": 0,
        "end_time": "2016-06-09 14:41:05",
        "type": "incoming"
    },
    {
        "calling": "u138v001",
        "callee": "u138",
        "init_time": "2016-06-09 17:32:04",
        "answered": true,
        "duration": 14,
        "end_time": "2016-06-09 17:32:25",
        "type": "incoming"
    },
    {
        "calling": "u138",
        "callee": "u138v002",
        "init_time": "2016-06-10 11:57:52",
        "answered": false,
        "duration": 0,
        "end_time": "2016-06-10 12:06:40",
        "type": "outgoing"
    },
    {
        "calling": "u138v001",
        "callee": "u138",
        "init_time": "2016-06-10 21:31:31",
        "answered": true,
        "duration": 104,
        "end_time": "2016-06-10 21:33:30",
        "type": "incoming"
    },
    {
        "calling": "u138v001",
        "callee": "u138",
        "init_time": "2016-06-10 21:37:55",
        "answered": true,
        "duration": 16,
        "end_time": "2016-06-10 21:38:27",
        "type": "incoming"
    },
    {
        "calling": "u138v001",
        "callee": "u138",
        "init_time": "2016-06-11 21:48:03",
        "answered": true,
        "duration": 17,
        "end_time": "2016-06-11 21:48:23",
        "type": "incoming"
    },
    {
        "calling": "u138v003",
        "callee": "u138",
        "init_time": "2016-06-15 14:22:25",
        "answered": false,
        "duration": 0,
        "end_time": "2016-06-15 14:22:55",
        "type": "incoming"
    },
    {
        "calling": "u138v003",
        "callee": "u138",
        "init_time": "2016-06-15 14:29:02",
        "answered": false,
        "duration": 0,
        "end_time": "2016-06-15 14:29:34",
        "type": "incoming"
    },
    {
        "calling": "u138v004",
        "callee": "u138",
        "init_time": "2016-06-15 15:30:07",
        "answered": false,
        "duration": 0,
        "end_time": "2016-06-15 15:30:39",
        "type": "incoming"
    },
    {
        "calling": "u138v004",
        "callee": "u138",
        "init_time": "2016-06-15 15:33:01",
        "answered": false,
        "duration": 0,
        "end_time": "2016-06-15 15:33:28",
        "type": "incoming"
    },
    {
        "calling": "u138v004",
        "callee": "u138",
        "init_time": "2016-06-15 15:49:38",
        "answered": false,
        "duration": 0,
        "end_time": "2016-06-15 15:49:59",
        "type": "incoming"
    },
    {
        "calling": "u138v005",
        "callee": "u138",
        "init_time": "2016-06-15 17:49:42",
        "answered": false,
        "duration": 0,
        "end_time": "2016-06-15 17:50:13",
        "type": "incoming"
    },
    {
        "calling": "u138v006",
        "callee": "u138",
        "init_time": "2016-06-16 09:49:47",
        "answered": false,
        "duration": 0,
        "end_time": "2016-06-16 09:50:18",
        "type": "incoming"
    },
    {
        "calling": "u138v004",
        "callee": "u138",
        "init_time": "2016-06-16 10:46:12",
        "answered": false,
        "duration": 0,
        "end_time": "2016-06-16 10:46:43",
        "type": "incoming"
    },
    {
        "calling": "u138v007",
        "callee": "u138",
        "init_time": "2016-06-17 13:48:35",
        "answered": false,
        "duration": 0,
        "end_time": "2016-06-17 13:49:06",
        "type": "incoming"
    },
    {
        "calling": "u138",
        "callee": "u138v001",
        "init_time": "2016-06-18 22:16:23",
        "answered": false,
        "duration": 0,
        "end_time": "2016-06-18 22:17:14",
        "type": "outgoing"
    },
    {
        "calling": "u138",
        "callee": "u138v008",
        "init_time": "2016-06-20 07:03:58",
        "answered": false,
        "duration": 0,
        "end_time": "2016-06-20 07:04:00",
        "type": "outgoing"
    },
    {
        "calling": "u138",
        "callee": "u138v008",
        "init_time": "2016-06-20 07:09:02",
        "answered": false,
        "duration": 0,
        "end_time": "2016-06-20 07:09:48",
        "type": "outgoing"
    },
    {
        "calling": "u138v007",
        "callee": "u138",
        "init_time": "2016-06-20 14:12:14",
        "answered": false,
        "duration": 0,
        "end_time": "2016-06-20 14:12:45",
        "type": "incoming"
    },
    {
        "calling": "u138v009",
        "callee": "u138",
        "init_time": "2016-06-20 18:16:22",
        "answered": false,
        "duration": 0,
        "end_time": "2016-06-20 18:16:47",
        "type": "incoming"
    },
    {
        "calling": "u138v010",
        "callee": "u138",
        "init_time": "2016-06-22 11:34:44",
        "answered": false,
        "duration": 0,
        "end_time": "2016-06-22 11:35:16",
        "type": "incoming"
    },
    {
        "calling": "u138v011",
        "callee": "u138",
        "init_time": "2016-06-23 12:36:01",
        "answered": false,
        "duration": 0,
        "end_time": "2016-06-23 12:36:32",
        "type": "incoming"
    },
    {
        "calling": "u138",
        "callee": "u138v008",
        "init_time": "2016-06-27 07:13:26",
        "answered": false,
        "duration": 0,
        "end_time": "2016-06-27 07:14:14",
        "type": "outgoing"
    },
    {
        "calling": "u138v012",
        "callee": "u138",
        "init_time": "2016-06-27 17:09:59",
        "answered": false,
        "duration": 0,
        "end_time": "2016-06-27 17:10:31",
        "type": "incoming"
    },
    {
        "calling": "u138v012",
        "callee": "u138",
        "init_time": "2016-06-27 17:10:43",
        "answered": false,
        "duration": 0,
        "end_time": "2016-06-27 17:11:14",
        "type": "incoming"
    },
    {
        "calling": "u138v013",
        "callee": "u138",
        "init_time": "2016-06-27 17:43:05",
        "answered": false,
        "duration": 0,
        "end_time": "2016-06-27 17:43:09",
        "type": "incoming"
    },
    {
        "calling": "u138v012",
        "callee": "u138",
        "init_time": "2016-06-27 18:06:02",
        "answered": false,
        "duration": 0,
        "end_time": "2016-06-27 18:06:34",
        "type": "incoming"
    },
    {
        "calling": "u138v001",
        "callee": "u138",
        "init_time": "2016-06-30 17:59:25",
        "answered": false,
        "duration": 0,
        "end_time": "2016-06-30 17:59:35",
        "type": "incoming"
    },
    {
        "calling": "u138",
        "callee": "u138v001",
        "init_time": "2016-06-30 17:59:51",
        "answered": false,
        "duration": 0,
        "end_time": "2016-06-30 18:00:09",
        "type": "outgoing"
    },
    {
        "calling": "u138v014",
        "callee": "u138",
        "init_time": "2016-06-30 19:12:16",
        "answered": false,
        "duration": 0,
        "end_time": "2016-06-30 19:12:37",
        "type": "incoming"
    },
    {
        "calling": "u138",
        "callee": "u138v014",
        "init_time": "2016-06-30 21:12:47",
        "answered": false,
        "duration": 0,
        "end_time": "2016-06-30 21:12:48",
        "type": "outgoing"
    },
    {
        "calling": "u138",
        "callee": "u138v008",
        "init_time": "2016-07-04 07:15:40",
        "answered": false,
        "duration": 0,
        "end_time": "2016-07-04 07:15:46",
        "type": "outgoing"
    },
    {
        "calling": "u138",
        "callee": "u138v008",
        "init_time": "2016-07-04 07:15:56",
        "answered": false,
        "duration": 0,
        "end_time": "2016-07-04 07:16:01",
        "type": "outgoing"
    },
    {
        "calling": "u138",
        "callee": "u138v008",
        "init_time": "2016-07-04 07:16:24",
        "answered": false,
        "duration": 0,
        "end_time": "2016-07-04 07:17:01",
        "type": "outgoing"
    },
    {
        "calling": "u138v015",
        "callee": "u138",
        "init_time": "2016-07-05 12:16:36",
        "answered": false,
        "duration": 0,
        "end_time": "2016-07-05 12:17:07",
        "type": "incoming"
    },
    {
        "calling": "u138v016",
        "callee": "u138",
        "init_time": "2016-07-05 12:29:52",
        "answered": false,
        "duration": 0,
        "end_time": "2016-07-05 12:30:17",
        "type": "incoming"
    },
    {
        "calling": "u138v017",
        "callee": "u138",
        "init_time": "2016-07-05 18:26:23",
        "answered": false,
        "duration": 0,
        "end_time": "2016-07-05 18:26:54",
        "type": "incoming"
    },
    {
        "calling": "u138v018",
        "callee": "u138",
        "init_time": "2016-07-06 13:25:25",
        "answered": true,
        "duration": 14,
        "end_time": "2016-07-06 13:25:42",
        "type": "incoming"
    },
    {
        "calling": "u138",
        "callee": "u138v001",
        "init_time": "2016-07-09 18:43:56",
        "answered": false,
        "duration": 0,
        "end_time": "2016-07-09 18:44:04",
        "type": "outgoing"
    },
    {
        "calling": "u138v001",
        "callee": "u138",
        "init_time": "2016-07-09 18:55:23",
        "answered": true,
        "duration": 23,
        "end_time": "2016-07-09 18:55:56",
        "type": "incoming"
    },
    {
        "calling": "u138",
        "callee": "u138v019",
        "init_time": "2016-07-11 10:34:42",
        "answered": false,
        "duration": 0,
        "end_time": "2016-07-11 10:36:07",
        "type": "outgoing"
    }
]