[
    {
        "calling": "u228v000",
        "callee": "u228",
        "init_time": "2016-06-17 16:55:46",
        "answered": true,
        "duration": 16,
        "end_time": "2016-06-17 16:56:19",
        "type": "incoming"
    },
    {
        "calling": "u228",
        "callee": "u228v001",
        "init_time": "2016-06-17 17:10:37",
        "answered": false,
        "duration": 0,
        "end_time": "2016-06-17 17:14:01",
        "type": "outgoing"
    },
    {
        "calling": "u228",
        "callee": "u228v002",
        "init_time": "2016-06-17 17:19:18",
        "answered": false,
        "duration": 0,
        "end_time": "2016-06-17 17:19:52",
        "type": "outgoing"
    },
    {
        "calling": "u228",
        "callee": "u228v000",
        "init_time": "2016-06-19 18:30:41",
        "answered": false,
        "duration": 0,
        "end_time": "2016-06-19 18:31:15",
        "type": "outgoing"
    },
    {
        "calling": "u228",
        "callee": "u228v003",
        "init_time": "2016-06-19 18:31:30",
        "answered": false,
        "duration": 0,
        "end_time": "2016-06-19 18:35:37",
        "type": "outgoing"
    },
    {
        "calling": "u228",
        "callee": "u228v004",
        "init_time": "2016-06-19 18:36:03",
        "answered": false,
        "duration": 0,
        "end_time": "2016-06-19 18:36:25",
        "type": "outgoing"
    },
    {
        "calling": "u228v005",
        "callee": "u228",
        "init_time": "2016-06-22 09:23:53",
        "answered": false,
        "duration": 0,
        "end_time": "2016-06-22 09:24:13",
        "type": "incoming"
    },
    {
        "calling": "u228v005",
        "callee": "u228",
        "init_time": "2016-06-22 09:36:45",
        "answered": false,
        "duration": 0,
        "end_time": "2016-06-22 09:37:06",
        "type": "incoming"
    },
    {
        "calling": "u228v006",
        "callee": "u228",
        "init_time": "2016-06-22 10:41:54",
        "answered": false,
        "duration": 0,
        "end_time": "2016-06-22 10:42:14",
        "type": "incoming"
    },
    {
        "calling": "u228",
        "callee": "u228v006",
        "init_time": "2016-06-22 11:10:55",
        "answered": false,
        "duration": 0,
        "end_time": "2016-06-22 11:11:45",
        "type": "outgoing"
    },
    {
        "calling": "u228",
        "callee": "u228v005",
        "init_time": "2016-06-22 11:27:22",
        "answered": false,
        "duration": 0,
        "end_time": "2016-06-22 11:27:24",
        "type": "outgoing"
    },
    {
        "calling": "u228",
        "callee": "u228v007",
        "init_time": "2016-06-22 11:27:35",
        "answered": false,
        "duration": 0,
        "end_time": "2016-06-22 11:35:10",
        "type": "outgoing"
    },
    {
        "calling": "u228",
        "callee": "u228v007",
        "init_time": "2016-06-22 11:36:08",
        "answered": false,
        "duration": 0,
        "end_time": "2016-06-22 11:37:09",
        "type": "outgoing"
    },
    {
        "calling": "u228",
        "callee": "u228v007",
        "init_time": "2016-06-22 11:37:15",
        "answered": false,
        "duration": 0,
        "end_time": "2016-06-22 11:49:12",
        "type": "outgoing"
    },
    {
        "calling": "u228",
        "callee": "u228v007",
        "init_time": "2016-06-22 11:49:12",
        "answered": false,
        "duration": 0,
        "end_time": "2016-06-22 11:49:14",
        "type": "outgoing"
    },
    {
        "calling": "u228",
        "callee": "u228v008",
        "init_time": "2016-06-22 13:53:08",
        "answered": false,
        "duration": 0,
        "end_time": "2016-06-22 13:53:28",
        "type": "outgoing"
    },
    {
        "calling": "u228",
        "callee": "u228v008",
        "init_time": "2016-06-22 14:01:07",
        "answered": false,
        "duration": 0,
        "end_time": "2016-06-22 14:01:28",
        "type": "outgoing"
    },
    {
        "calling": "u228",
        "callee": "u228v009",
        "init_time": "2016-06-22 14:01:56",
        "answered": false,
        "duration": 0,
        "end_time": "2016-06-22 14:02:27",
        "type": "outgoing"
    },
    {
        "calling": "u228v009",
        "callee": "u228",
        "init_time": "2016-06-22 14:31:08",
        "answered": true,
        "duration": 39,
        "end_time": "2016-06-22 14:31:50",
        "type": "incoming"
    },
    {
        "calling": "u228",
        "callee": "u228v010",
        "init_time": "2016-06-22 16:45:47",
        "answered": false,
        "duration": 0,
        "end_time": "2016-06-22 16:46:46",
        "type": "outgoing"
    },
    {
        "calling": "u228",
        "callee": "u228v011",
        "init_time": "2016-06-22 16:47:28",
        "answered": false,
        "duration": 0,
        "end_time": "2016-06-22 16:49:16",
        "type": "outgoing"
    },
    {
        "calling": "u228",
        "callee": "u228v000",
        "init_time": "2016-06-22 19:07:44",
        "answered": false,
        "duration": 0,
        "end_time": "2016-06-22 19:08:19",
        "type": "outgoing"
    },
    {
        "calling": "u228",
        "callee": "u228v003",
        "init_time": "2016-06-22 19:08:34",
        "answered": false,
        "duration": 0,
        "end_time": "2016-06-22 19:09:26",
        "type": "outgoing"
    },
    {
        "calling": "u228",
        "callee": "u228v000",
        "init_time": "2016-06-22 19:09:40",
        "answered": false,
        "duration": 0,
        "end_time": "2016-06-22 19:10:54",
        "type": "outgoing"
    },
    {
        "calling": "u228v000",
        "callee": "u228",
        "init_time": "2016-06-22 19:38:13",
        "answered": true,
        "duration": 121,
        "end_time": "2016-06-22 19:40:21",
        "type": "incoming"
    },
    {
        "calling": "u228",
        "callee": "u228v011",
        "init_time": "2016-06-22 19:41:28",
        "answered": false,
        "duration": 0,
        "end_time": "2016-06-22 19:42:17",
        "type": "outgoing"
    },
    {
        "calling": "u228",
        "callee": "u228v012",
        "init_time": "2016-06-24 22:21:58",
        "answered": false,
        "duration": 0,
        "end_time": "2016-06-24 22:24:23",
        "type": "outgoing"
    },
    {
        "calling": "u228v000",
        "callee": "u228",
        "init_time": "2016-06-24 22:28:57",
        "answered": true,
        "duration": 167,
        "end_time": "2016-06-24 22:31:47",
        "type": "incoming"
    },
    {
        "calling": "u228",
        "callee": "u228v012",
        "init_time": "2016-06-24 22:34:24",
        "answered": false,
        "duration": 0,
        "end_time": "2016-06-24 22:34:43",
        "type": "outgoing"
    },
    {
        "calling": "u228v000",
        "callee": "u228",
        "init_time": "2016-06-25 08:30:51",
        "answered": true,
        "duration": 34,
        "end_time": "2016-06-25 08:31:35",
        "type": "incoming"
    },
    {
        "calling": "u228",
        "callee": "u228v000",
        "init_time": "2016-06-25 08:53:15",
        "answered": false,
        "duration": 0,
        "end_time": "2016-06-25 08:53:17",
        "type": "outgoing"
    },
    {
        "calling": "u228",
        "callee": "u228v000",
        "init_time": "2016-06-25 09:05:58",
        "answered": false,
        "duration": 0,
        "end_time": "2016-06-25 09:06:34",
        "type": "outgoing"
    },
    {
        "calling": "u228v005",
        "callee": "u228",
        "init_time": "2016-06-25 09:38:53",
        "answered": true,
        "duration": 20,
        "end_time": "2016-06-25 09:39:26",
        "type": "incoming"
    },
    {
        "calling": "u228v013",
        "callee": "u228",
        "init_time": "2016-06-25 11:28:27",
        "answered": true,
        "duration": 43,
        "end_time": "2016-06-25 11:29:25",
        "type": "incoming"
    },
    {
        "calling": "u228v014",
        "callee": "u228",
        "init_time": "2016-06-25 12:51:24",
        "answered": false,
        "duration": 0,
        "end_time": "2016-06-25 12:51:45",
        "type": "incoming"
    },
    {
        "calling": "u228",
        "callee": "u228v014",
        "init_time": "2016-06-25 13:00:30",
        "answered": false,
        "duration": 0,
        "end_time": "2016-06-25 13:01:24",
        "type": "outgoing"
    },
    {
        "calling": "u228",
        "callee": "u228v000",
        "init_time": "2016-06-25 15:45:55",
        "answered": false,
        "duration": 0,
        "end_time": "2016-06-25 15:48:15",
        "type": "outgoing"
    },
    {
        "calling": "u228v000",
        "callee": "u228",
        "init_time": "2016-06-25 19:56:54",
        "answered": true,
        "duration": 60,
        "end_time": "2016-06-25 19:58:07",
        "type": "incoming"
    },
    {
        "calling": "u228v000",
        "callee": "u228",
        "init_time": "2016-06-25 19:58:23",
        "answered": true,
        "duration": 32,
        "end_time": "2016-06-25 19:58:59",
        "type": "incoming"
    },
    {
        "calling": "u228",
        "callee": "u228v000",
        "init_time": "2016-06-25 20:14:10",
        "answered": false,
        "duration": 0,
        "end_time": "2016-06-25 20:14:13",
        "type": "outgoing"
    },
    {
        "calling": "u228",
        "callee": "u228v001",
        "init_time": "2016-06-25 21:24:33",
        "answered": false,
        "duration": 0,
        "end_time": "2016-06-25 21:25:29",
        "type": "outgoing"
    },
    {
        "calling": "u228v001",
        "callee": "u228",
        "init_time": "2016-06-25 21:28:26",
        "answered": true,
        "duration": 262,
        "end_time": "2016-06-25 21:32:52",
        "type": "incoming"
    },
    {
        "calling": "u228",
        "callee": "u228v015",
        "init_time": "2016-06-28 12:16:52",
        "answered": false,
        "duration": 0,
        "end_time": "2016-06-28 12:17:01",
        "type": "outgoing"
    },
    {
        "calling": "u228v000",
        "callee": "u228",
        "init_time": "2016-06-28 12:44:25",
        "answered": false,
        "duration": 0,
        "end_time": "2016-06-28 12:44:47",
        "type": "incoming"
    },
    {
        "calling": "u228",
        "callee": "u228v000",
        "init_time": "2016-06-28 12:54:26",
        "answered": false,
        "duration": 0,
        "end_time": "2016-06-28 12:55:46",
        "type": "outgoing"
    },
    {
        "calling": "u228",
        "callee": "u228v000",
        "init_time": "2016-06-28 15:08:37",
        "answered": false,
        "duration": 0,
        "end_time": "2016-06-28 15:10:22",
        "type": "outgoing"
    },
    {
        "calling": "u228",
        "callee": "u228v000",
        "init_time": "2016-06-28 16:37:33",
        "answered": false,
        "duration": 0,
        "end_time": "2016-06-28 16:38:04",
        "type": "outgoing"
    },
    {
        "calling": "u228",
        "callee": "u228v012",
        "init_time": "2016-06-28 16:39:03",
        "answered": false,
        "duration": 0,
        "end_time": "2016-06-28 16:39:29",
        "type": "outgoing"
    },
    {
        "calling": "u228",
        "callee": "u228v000",
        "init_time": "2016-06-28 16:41:34",
        "answered": false,
        "duration": 0,
        "end_time": "2016-06-28 16:41:38",
        "type": "outgoing"
    },
    {
        "calling": "u228v016",
        "callee": "u228",
        "init_time": "2016-06-28 17:07:05",
        "answered": false,
        "duration": 0,
        "end_time": "2016-06-28 17:07:25",
        "type": "incoming"
    },
    {
        "calling": "u228",
        "callee": "u228v016",
        "init_time": "2016-06-28 18:19:44",
        "answered": false,
        "duration": 0,
        "end_time": "2016-06-28 18:20:18",
        "type": "outgoing"
    },
    {
        "calling": "u228v016",
        "callee": "u228",
        "init_time": "2016-06-28 18:20:34",
        "answered": true,
        "duration": 34,
        "end_time": "2016-06-28 18:21:18",
        "type": "incoming"
    },
    {
        "calling": "u228v000",
        "callee": "u228",
        "init_time": "2016-06-28 20:59:29",
        "answered": true,
        "duration": 38,
        "end_time": "2016-06-28 21:00:13",
        "type": "incoming"
    },
    {
        "calling": "u228",
        "callee": "u228v012",
        "init_time": "2016-06-29 15:01:34",
        "answered": false,
        "duration": 0,
        "end_time": "2016-06-29 15:02:58",
        "type": "outgoing"
    },
    {
        "calling": "u228",
        "callee": "u228v012",
        "init_time": "2016-06-29 16:08:00",
        "answered": false,
        "duration": 0,
        "end_time": "2016-06-29 16:08:29",
        "type": "outgoing"
    },
    {
        "calling": "u228v000",
        "callee": "u228",
        "init_time": "2016-06-29 17:53:26",
        "answered": true,
        "duration": 64,
        "end_time": "2016-06-29 17:54:35",
        "type": "incoming"
    },
    {
        "calling": "u228",
        "callee": "u228v000",
        "init_time": "2016-06-29 18:09:15",
        "answered": false,
        "duration": 0,
        "end_time": "2016-06-29 18:10:59",
        "type": "outgoing"
    },
    {
        "calling": "u228v000",
        "callee": "u228",
        "init_time": "2016-06-29 19:33:23",
        "answered": false,
        "duration": 0,
        "end_time": "2016-06-29 19:33:44",
        "type": "incoming"
    },
    {
        "calling": "u228",
        "callee": "u228v000",
        "init_time": "2016-06-29 19:33:52",
        "answered": false,
        "duration": 0,
        "end_time": "2016-06-29 19:34:45",
        "type": "outgoing"
    },
    {
        "calling": "u228",
        "callee": "u228v012",
        "init_time": "2016-06-29 19:40:45",
        "answered": false,
        "duration": 0,
        "end_time": "2016-06-29 19:41:10",
        "type": "outgoing"
    },
    {
        "calling": "u228v009",
        "callee": "u228",
        "init_time": "2016-06-29 20:12:52",
        "answered": false,
        "duration": 0,
        "end_time": "2016-06-29 20:13:13",
        "type": "incoming"
    },
    {
        "calling": "u228",
        "callee": "u228v009",
        "init_time": "2016-06-29 20:13:20",
        "answered": false,
        "duration": 0,
        "end_time": "2016-06-29 20:13:29",
        "type": "outgoing"
    },
    {
        "calling": "u228",
        "callee": "u228v009",
        "init_time": "2016-06-29 20:13:38",
        "answered": false,
        "duration": 0,
        "end_time": "2016-06-29 20:13:45",
        "type": "outgoing"
    },
    {
        "calling": "u228",
        "callee": "u228v009",
        "init_time": "2016-06-29 20:16:37",
        "answered": false,
        "duration": 0,
        "end_time": "2016-06-29 20:17:22",
        "type": "outgoing"
    },
    {
        "calling": "u228v000",
        "callee": "u228",
        "init_time": "2016-06-29 20:48:57",
        "answered": true,
        "duration": 126,
        "end_time": "2016-06-29 20:51:15",
        "type": "incoming"
    },
    {
        "calling": "u228",
        "callee": "u228v000",
        "init_time": "2016-06-29 21:45:28",
        "answered": false,
        "duration": 0,
        "end_time": "2016-06-29 21:46:45",
        "type": "outgoing"
    },
    {
        "calling": "u228",
        "callee": "u228v017",
        "init_time": "2016-06-30 09:41:40",
        "answered": false,
        "duration": 0,
        "end_time": "2016-06-30 09:43:13",
        "type": "outgoing"
    },
    {
        "calling": "u228",
        "callee": "u228v018",
        "init_time": "2016-06-30 09:59:06",
        "answered": false,
        "duration": 0,
        "end_time": "2016-06-30 09:59:46",
        "type": "outgoing"
    },
    {
        "calling": "u228",
        "callee": "u228v019",
        "init_time": "2016-06-30 09:59:49",
        "answered": false,
        "duration": 0,
        "end_time": "2016-06-30 10:02:58",
        "type": "outgoing"
    },
    {
        "calling": "u228v002",
        "callee": "u228",
        "init_time": "2016-06-30 14:03:28",
        "answered": false,
        "duration": 0,
        "end_time": "2016-06-30 14:03:48",
        "type": "incoming"
    },
    {
        "calling": "u228",
        "callee": "u228v000",
        "init_time": "2016-06-30 14:11:11",
        "answered": false,
        "duration": 0,
        "end_time": "2016-06-30 14:11:44",
        "type": "outgoing"
    },
    {
        "calling": "u228",
        "callee": "u228v020",
        "init_time": "2016-06-30 14:36:58",
        "answered": false,
        "duration": 0,
        "end_time": "2016-06-30 14:37:27",
        "type": "outgoing"
    },
    {
        "calling": "u228",
        "callee": "u228v012",
        "init_time": "2016-06-30 14:39:31",
        "answered": false,
        "duration": 0,
        "end_time": "2016-06-30 14:39:55",
        "type": "outgoing"
    },
    {
        "calling": "u228v000",
        "callee": "u228",
        "init_time": "2016-06-30 14:41:56",
        "answered": true,
        "duration": 34,
        "end_time": "2016-06-30 14:42:37",
        "type": "incoming"
    },
    {
        "calling": "u228",
        "callee": "u228v003",
        "init_time": "2016-06-30 20:31:04",
        "answered": false,
        "duration": 0,
        "end_time": "2016-06-30 20:32:39",
        "type": "outgoing"
    },
    {
        "calling": "u228",
        "callee": "u228v021",
        "init_time": "2016-06-30 20:45:01",
        "answered": false,
        "duration": 0,
        "end_time": "2016-06-30 20:45:10",
        "type": "outgoing"
    },
    {
        "calling": "u228",
        "callee": "u228v022",
        "init_time": "2016-06-30 20:45:15",
        "answered": false,
        "duration": 0,
        "end_time": "2016-06-30 20:45:53",
        "type": "outgoing"
    },
    {
        "calling": "u228",
        "callee": "u228v022",
        "init_time": "2016-06-30 20:52:36",
        "answered": false,
        "duration": 0,
        "end_time": "2016-06-30 20:54:12",
        "type": "outgoing"
    },
    {
        "calling": "u228",
        "callee": "u228v022",
        "init_time": "2016-06-30 21:27:38",
        "answered": false,
        "duration": 0,
        "end_time": "2016-06-30 21:28:04",
        "type": "outgoing"
    },
    {
        "calling": "u228",
        "callee": "u228v009",
        "init_time": "2016-06-30 21:28:11",
        "answered": false,
        "duration": 0,
        "end_time": "2016-06-30 21:28:44",
        "type": "outgoing"
    },
    {
        "calling": "u228",
        "callee": "u228v009",
        "init_time": "2016-06-30 21:31:05",
        "answered": false,
        "duration": 0,
        "end_time": "2016-06-30 21:31:41",
        "type": "outgoing"
    },
    {
        "calling": "u228",
        "callee": "u228v009",
        "init_time": "2016-06-30 21:33:29",
        "answered": false,
        "duration": 0,
        "end_time": "2016-06-30 21:34:06",
        "type": "outgoing"
    },
    {
        "calling": "u228",
        "callee": "u228v009",
        "init_time": "2016-06-30 22:39:15",
        "answered": false,
        "duration": 0,
        "end_time": "2016-06-30 22:39:52",
        "type": "outgoing"
    },
    {
        "calling": "u228v009",
        "callee": "u228",
        "init_time": "2016-06-30 22:41:01",
        "answered": false,
        "duration": 0,
        "end_time": "2016-06-30 22:41:22",
        "type": "incoming"
    },
    {
        "calling": "u228v009",
        "callee": "u228",
        "init_time": "2016-06-30 22:52:24",
        "answered": false,
        "duration": 0,
        "end_time": "2016-06-30 22:52:45",
        "type": "incoming"
    },
    {
        "calling": "u228",
        "callee": "u228v023",
        "init_time": "2016-07-01 11:08:54",
        "answered": false,
        "duration": 0,
        "end_time": "2016-07-01 11:10:48",
        "type": "outgoing"
    },
    {
        "calling": "u228v024",
        "callee": "u228",
        "init_time": "2016-07-01 14:32:38",
        "answered": false,
        "duration": 0,
        "end_time": "2016-07-01 14:32:58",
        "type": "incoming"
    },
    {
        "calling": "u228v024",
        "callee": "u228",
        "init_time": "2016-07-01 14:44:58",
        "answered": false,
        "duration": 0,
        "end_time": "2016-07-01 14:45:18",
        "type": "incoming"
    },
    {
        "calling": "u228",
        "callee": "u228v024",
        "init_time": "2016-07-01 14:55:26",
        "answered": false,
        "duration": 0,
        "end_time": "2016-07-01 14:56:30",
        "type": "outgoing"
    },
    {
        "calling": "u228",
        "callee": "u228v003",
        "init_time": "2016-07-01 14:57:57",
        "answered": false,
        "duration": 0,
        "end_time": "2016-07-01 14:59:38",
        "type": "outgoing"
    },
    {
        "calling": "u228",
        "callee": "u228v012",
        "init_time": "2016-07-01 17:20:02",
        "answered": false,
        "duration": 0,
        "end_time": "2016-07-01 17:20:44",
        "type": "outgoing"
    },
    {
        "calling": "u228v012",
        "callee": "u228",
        "init_time": "2016-07-01 17:21:50",
        "answered": true,
        "duration": 28,
        "end_time": "2016-07-01 17:22:39",
        "type": "incoming"
    },
    {
        "calling": "u228",
        "callee": "u228v012",
        "init_time": "2016-07-01 17:22:47",
        "answered": false,
        "duration": 0,
        "end_time": "2016-07-01 17:24:53",
        "type": "outgoing"
    },
    {
        "calling": "u228",
        "callee": "u228v009",
        "init_time": "2016-07-01 17:27:25",
        "answered": false,
        "duration": 0,
        "end_time": "2016-07-01 17:28:51",
        "type": "outgoing"
    },
    {
        "calling": "u228",
        "callee": "u228v012",
        "init_time": "2016-07-01 21:22:16",
        "answered": false,
        "duration": 0,
        "end_time": "2016-07-01 21:34:26",
        "type": "outgoing"
    },
    {
        "calling": "u228",
        "callee": "u228v000",
        "init_time": "2016-07-06 22:44:16",
        "answered": false,
        "duration": 0,
        "end_time": "2016-07-06 22:44:23",
        "type": "outgoing"
    },
    {
        "calling": "u228",
        "callee": "u228v000",
        "init_time": "2016-07-06 22:44:59",
        "answered": false,
        "duration": 0,
        "end_time": "2016-07-06 22:45:06",
        "type": "outgoing"
    },
    {
        "calling": "u228v016",
        "callee": "u228",
        "init_time": "2016-07-07 14:46:41",
        "answered": false,
        "duration": 0,
        "end_time": "2016-07-07 14:47:02",
        "type": "incoming"
    },
    {
        "calling": "u228v022",
        "callee": "u228",
        "init_time": "2016-07-07 15:15:09",
        "answered": false,
        "duration": 0,
        "end_time": "2016-07-07 15:15:29",
        "type": "incoming"
    },
    {
        "calling": "u228",
        "callee": "u228v016",
        "init_time": "2016-07-07 15:32:26",
        "answered": false,
        "duration": 0,
        "end_time": "2016-07-07 15:33:36",
        "type": "outgoing"
    },
    {
        "calling": "u228v025",
        "callee": "u228",
        "init_time": "2016-07-07 17:00:53",
        "answered": true,
        "duration": 17,
        "end_time": "2016-07-07 17:01:16",
        "type": "incoming"
    },
    {
        "calling": "u228",
        "callee": "u228v004",
        "init_time": "2016-07-07 17:16:22",
        "answered": false,
        "duration": 0,
        "end_time": "2016-07-07 17:18:32",
        "type": "outgoing"
    },
    {
        "calling": "u228",
        "callee": "u228v004",
        "init_time": "2016-07-07 17:19:20",
        "answered": false,
        "duration": 0,
        "end_time": "2016-07-07 17:24:06",
        "type": "outgoing"
    },
    {
        "calling": "u228",
        "callee": "u228v026",
        "init_time": "2016-07-07 17:28:29",
        "answered": false,
        "duration": 0,
        "end_time": "2016-07-07 17:50:44",
        "type": "outgoing"
    },
    {
        "calling": "u228v026",
        "callee": "u228",
        "init_time": "2016-07-07 17:52:56",
        "answered": false,
        "duration": 0,
        "end_time": "2016-07-07 17:53:17",
        "type": "incoming"
    },
    {
        "calling": "u228",
        "callee": "u228v012",
        "init_time": "2016-07-07 18:38:13",
        "answered": false,
        "duration": 0,
        "end_time": "2016-07-07 18:43:16",
        "type": "outgoing"
    },
    {
        "calling": "u228v012",
        "callee": "u228",
        "init_time": "2016-07-07 19:32:28",
        "answered": true,
        "duration": 152,
        "end_time": "2016-07-07 19:35:04",
        "type": "incoming"
    },
    {
        "calling": "u228",
        "callee": "u228v012",
        "init_time": "2016-07-07 21:24:51",
        "answered": false,
        "duration": 0,
        "end_time": "2016-07-07 21:35:59",
        "type": "outgoing"
    },
    {
        "calling": "u228",
        "callee": "u228v004",
        "init_time": "2016-07-08 10:53:52",
        "answered": false,
        "duration": 0,
        "end_time": "2016-07-08 10:55:27",
        "type": "outgoing"
    },
    {
        "calling": "u228",
        "callee": "u228v027",
        "init_time": "2016-07-08 12:09:36",
        "answered": false,
        "duration": 0,
        "end_time": "2016-07-08 12:10:30",
        "type": "outgoing"
    },
    {
        "calling": "u228",
        "callee": "u228v028",
        "init_time": "2016-07-08 16:39:03",
        "answered": false,
        "duration": 0,
        "end_time": "2016-07-08 16:39:24",
        "type": "outgoing"
    },
    {
        "calling": "u228",
        "callee": "u228v012",
        "init_time": "2016-07-08 18:42:59",
        "answered": false,
        "duration": 0,
        "end_time": "2016-07-08 18:45:03",
        "type": "outgoing"
    },
    {
        "calling": "u228",
        "callee": "u228v012",
        "init_time": "2016-07-08 18:55:17",
        "answered": false,
        "duration": 0,
        "end_time": "2016-07-08 18:55:37",
        "type": "outgoing"
    },
    {
        "calling": "u228",
        "callee": "u228v027",
        "init_time": "2016-07-09 01:59:39",
        "answered": false,
        "duration": 0,
        "end_time": "2016-07-09 02:00:59",
        "type": "outgoing"
    },
    {
        "calling": "u228",
        "callee": "u228v029",
        "init_time": "2016-07-09 02:01:51",
        "answered": false,
        "duration": 0,
        "end_time": "2016-07-09 02:05:19",
        "type": "outgoing"
    },
    {
        "calling": "u228",
        "callee": "u228v029",
        "init_time": "2016-07-09 02:12:45",
        "answered": false,
        "duration": 0,
        "end_time": "2016-07-09 02:14:19",
        "type": "outgoing"
    },
    {
        "calling": "u228",
        "callee": "u228v027",
        "init_time": "2016-07-09 02:14:27",
        "answered": false,
        "duration": 0,
        "end_time": "2016-07-09 02:14:44",
        "type": "outgoing"
    },
    {
        "calling": "u228v009",
        "callee": "u228",
        "init_time": "2016-07-10 17:30:53",
        "answered": false,
        "duration": 0,
        "end_time": "2016-07-10 17:31:13",
        "type": "incoming"
    },
    {
        "calling": "u228",
        "callee": "u228v009",
        "init_time": "2016-07-10 18:23:32",
        "answered": false,
        "duration": 0,
        "end_time": "2016-07-10 18:27:20",
        "type": "outgoing"
    },
    {
        "calling": "u228",
        "callee": "u228v030",
        "init_time": "2016-07-10 18:27:31",
        "answered": false,
        "duration": 0,
        "end_time": "2016-07-10 18:27:43",
        "type": "outgoing"
    },
    {
        "calling": "u228",
        "callee": "u228v031",
        "init_time": "2016-07-10 18:28:00",
        "answered": false,
        "duration": 0,
        "end_time": "2016-07-10 18:34:21",
        "type": "outgoing"
    },
    {
        "calling": "u228",
        "callee": "u228v031",
        "init_time": "2016-07-10 18:34:22",
        "answered": false,
        "duration": 0,
        "end_time": "2016-07-10 18:36:05",
        "type": "outgoing"
    },
    {
        "calling": "u228v031",
        "callee": "u228",
        "init_time": "2016-07-10 18:36:47",
        "answered": true,
        "duration": 114,
        "end_time": "2016-07-10 18:38:52",
        "type": "incoming"
    },
    {
        "calling": "u228",
        "callee": "u228v002",
        "init_time": "2016-07-11 13:09:22",
        "answered": false,
        "duration": 0,
        "end_time": "2016-07-11 13:09:48",
        "type": "outgoing"
    },
    {
        "calling": "u228",
        "callee": "u228v032",
        "init_time": "2016-07-11 13:11:28",
        "answered": false,
        "duration": 0,
        "end_time": "2016-07-11 13:12:39",
        "type": "outgoing"
    },
    {
        "calling": "u228",
        "callee": "u228v002",
        "init_time": "2016-07-11 13:12:50",
        "answered": false,
        "duration": 0,
        "end_time": "2016-07-11 13:13:20",
        "type": "outgoing"
    },
    {
        "calling": "u228v002",
        "callee": "u228",
        "init_time": "2016-07-11 13:36:27",
        "answered": false,
        "duration": 0,
        "end_time": "2016-07-11 13:36:48",
        "type": "incoming"
    },
    {
        "calling": "u228",
        "callee": "u228v012",
        "init_time": "2016-07-11 13:56:19",
        "answered": false,
        "duration": 0,
        "end_time": "2016-07-11 13:56:27",
        "type": "outgoing"
    },
    {
        "calling": "u228",
        "callee": "u228v012",
        "init_time": "2016-07-11 13:57:33",
        "answered": false,
        "duration": 0,
        "end_time": "2016-07-11 13:57:43",
        "type": "outgoing"
    },
    {
        "calling": "u228",
        "callee": "u228v012",
        "init_time": "2016-07-11 13:57:45",
        "answered": false,
        "duration": 0,
        "end_time": "2016-07-11 13:57:48",
        "type": "outgoing"
    },
    {
        "calling": "u228",
        "callee": "u228v012",
        "init_time": "2016-07-11 13:57:54",
        "answered": false,
        "duration": 0,
        "end_time": "2016-07-11 13:58:02",
        "type": "outgoing"
    },
    {
        "calling": "u228",
        "callee": "u228v033",
        "init_time": "2016-07-11 13:58:11",
        "answered": false,
        "duration": 0,
        "end_time": "2016-07-11 13:58:52",
        "type": "outgoing"
    },
    {
        "calling": "u228",
        "callee": "u228v034",
        "init_time": "2016-07-11 13:59:20",
        "answered": false,
        "duration": 0,
        "end_time": "2016-07-11 14:00:03",
        "type": "outgoing"
    },
    {
        "calling": "u228",
        "callee": "u228v035",
        "init_time": "2016-07-11 14:00:10",
        "answered": false,
        "duration": 0,
        "end_time": "2016-07-11 14:00:12",
        "type": "outgoing"
    },
    {
        "calling": "u228",
        "callee": "u228v035",
        "init_time": "2016-07-11 14:00:19",
        "answered": false,
        "duration": 0,
        "end_time": "2016-07-11 14:00:21",
        "type": "outgoing"
    },
    {
        "calling": "u228",
        "callee": "u228v036",
        "init_time": "2016-07-11 14:00:29",
        "answered": false,
        "duration": 0,
        "end_time": "2016-07-11 14:00:31",
        "type": "outgoing"
    },
    {
        "calling": "u228",
        "callee": "u228v036",
        "init_time": "2016-07-11 14:00:40",
        "answered": false,
        "duration": 0,
        "end_time": "2016-07-11 14:00:43",
        "type": "outgoing"
    },
    {
        "calling": "u228",
        "callee": "u228v035",
        "init_time": "2016-07-11 14:00:55",
        "answered": false,
        "duration": 0,
        "end_time": "2016-07-11 14:00:58",
        "type": "outgoing"
    },
    {
        "calling": "u228",
        "callee": "u228v036",
        "init_time": "2016-07-11 14:01:14",
        "answered": false,
        "duration": 0,
        "end_time": "2016-07-11 14:03:34",
        "type": "outgoing"
    },
    {
        "calling": "u228",
        "callee": "u228v034",
        "init_time": "2016-07-11 14:05:01",
        "answered": false,
        "duration": 0,
        "end_time": "2016-07-11 14:05:40",
        "type": "outgoing"
    },
    {
        "calling": "u228",
        "callee": "u228v037",
        "init_time": "2016-07-11 14:08:02",
        "answered": false,
        "duration": 0,
        "end_time": "2016-07-11 14:08:53",
        "type": "outgoing"
    },
    {
        "calling": "u228",
        "callee": "u228v037",
        "init_time": "2016-07-11 14:09:04",
        "answered": false,
        "duration": 0,
        "end_time": "2016-07-11 14:10:05",
        "type": "outgoing"
    },
    {
        "calling": "u228",
        "callee": "u228v037",
        "init_time": "2016-07-11 14:10:46",
        "answered": false,
        "duration": 0,
        "end_time": "2016-07-11 14:14:27",
        "type": "outgoing"
    },
    {
        "calling": "u228",
        "callee": "u228v002",
        "init_time": "2016-07-11 14:14:56",
        "answered": false,
        "duration": 0,
        "end_time": "2016-07-11 14:15:55",
        "type": "outgoing"
    },
    {
        "calling": "u228",
        "callee": "u228v038",
        "init_time": "2016-07-11 14:16:01",
        "answered": false,
        "duration": 0,
        "end_time": "2016-07-11 14:16:05",
        "type": "outgoing"
    },
    {
        "calling": "u228",
        "callee": "u228v039",
        "init_time": "2016-07-11 14:16:12",
        "answered": false,
        "duration": 0,
        "end_time": "2016-07-11 14:16:22",
        "type": "outgoing"
    },
    {
        "calling": "u228",
        "callee": "u228v039",
        "init_time": "2016-07-11 14:16:35",
        "answered": false,
        "duration": 0,
        "end_time": "2016-07-11 14:21:23",
        "type": "outgoing"
    },
    {
        "calling": "u228",
        "callee": "u228v002",
        "init_time": "2016-07-11 14:21:25",
        "answered": false,
        "duration": 0,
        "end_time": "2016-07-11 14:23:13",
        "type": "outgoing"
    },
    {
        "calling": "u228",
        "callee": "u228v040",
        "init_time": "2016-07-11 14:23:39",
        "answered": false,
        "duration": 0,
        "end_time": "2016-07-11 14:23:41",
        "type": "outgoing"
    },
    {
        "calling": "u228",
        "callee": "u228v041",
        "init_time": "2016-07-11 14:23:54",
        "answered": false,
        "duration": 0,
        "end_time": "2016-07-11 14:28:26",
        "type": "outgoing"
    },
    {
        "calling": "u228",
        "callee": "u228v042",
        "init_time": "2016-07-11 14:28:55",
        "answered": false,
        "duration": 0,
        "end_time": "2016-07-11 14:29:51",
        "type": "outgoing"
    },
    {
        "calling": "u228",
        "callee": "u228v042",
        "init_time": "2016-07-11 16:18:24",
        "answered": false,
        "duration": 0,
        "end_time": "2016-07-11 16:19:23",
        "type": "outgoing"
    },
    {
        "calling": "u228",
        "callee": "u228v022",
        "init_time": "2016-07-11 16:37:58",
        "answered": false,
        "duration": 0,
        "end_time": "2016-07-11 16:38:11",
        "type": "outgoing"
    },
    {
        "calling": "u228",
        "callee": "u228v022",
        "init_time": "2016-07-11 16:38:20",
        "answered": false,
        "duration": 0,
        "end_time": "2016-07-11 16:38:28",
        "type": "outgoing"
    },
    {
        "calling": "u228v043",
        "callee": "u228",
        "init_time": "2016-07-11 17:15:57",
        "answered": false,
        "duration": 0,
        "end_time": "2016-07-11 17:16:16",
        "type": "incoming"
    },
    {
        "calling": "u228",
        "callee": "u228v043",
        "init_time": "2016-07-11 17:24:36",
        "answered": false,
        "duration": 0,
        "end_time": "2016-07-11 17:24:49",
        "type": "outgoing"
    },
    {
        "calling": "u228",
        "callee": "u228v022",
        "init_time": "2016-07-11 19:49:20",
        "answered": false,
        "duration": 0,
        "end_time": "2016-07-11 19:49:31",
        "type": "outgoing"
    },
    {
        "calling": "u228",
        "callee": "u228v022",
        "init_time": "2016-07-11 20:32:38",
        "answered": false,
        "duration": 0,
        "end_time": "2016-07-11 20:34:52",
        "type": "outgoing"
    },
    {
        "calling": "u228",
        "callee": "u228v022",
        "init_time": "2016-07-11 21:11:03",
        "answered": false,
        "duration": 0,
        "end_time": "2016-07-11 21:11:52",
        "type": "outgoing"
    },
    {
        "calling": "u228",
        "callee": "u228v009",
        "init_time": "2016-07-11 21:13:34",
        "answered": false,
        "duration": 0,
        "end_time": "2016-07-11 21:14:38",
        "type": "outgoing"
    },
    {
        "calling": "u228",
        "callee": "u228v009",
        "init_time": "2016-07-11 21:14:49",
        "answered": false,
        "duration": 0,
        "end_time": "2016-07-11 21:16:09",
        "type": "outgoing"
    }
]